<annotation>
	<folder>images_yolo</folder>
	<filename>SIMATECIMAG59.jpg</filename>
	<path>C:\Documents_ancien_PC\ISEN\M1\chronic_wounds_project\data\images_yolo\SIMATECIMAG59.jpg</path>
	<source>
		<database>Unknown</database>
	</source>
	<size>
		<width>640</width>
		<height>640</height>
		<depth>3</depth>
	</size>
	<segmented>0</segmented>
	<object>
		<name>wound</name>
		<pose>Unspecified</pose>
		<truncated>0</truncated>
		<difficult>0</difficult>
		<bndbox>
			<xmin>274</xmin>
			<ymin>338</ymin>
			<xmax>367</xmax>
			<ymax>413</ymax>
		</bndbox>
	</object>
	<object>
		<name>calibration</name>
		<pose>Unspecified</pose>
		<truncated>0</truncated>
		<difficult>0</difficult>
		<bndbox>
			<xmin>285</xmin>
			<ymin>259</ymin>
			<xmax>364</xmax>
			<ymax>338</ymax>
		</bndbox>
	</object>
</annotation>
